cedar_graph/__init__.py
cedar_graph/_version.py
cedar_graph/logger.py
cedar_graph/metadata.py
cedar_graph/quickplot.py
cedar_graph/data/__init__.py
cedar_graph/data/field_info.py
cedar_graph/data/loader.py
cedar_graph/data/operator.py
cedar_graph/data/source.py
cedar_graph/plots/__init__.py
cedar_graph/plots/cn/__init__.py
cedar_graph/plots/cn/bpli_wind/__init__.py
cedar_graph/plots/cn/bpli_wind/default.py
cedar_graph/plots/cn/cape_wind/__init__.py
cedar_graph/plots/cn/cape_wind/default.py
cedar_graph/plots/cn/cin_wind/__init__.py
cedar_graph/plots/cn/cin_wind/default.py
cedar_graph/plots/cn/div_wind/__init__.py
cedar_graph/plots/cn/div_wind/default.py
cedar_graph/plots/cn/height_500_mslp/__init__.py
cedar_graph/plots/cn/height_500_mslp/default.py
cedar_graph/plots/cn/height_500_wind_850/__init__.py
cedar_graph/plots/cn/height_500_wind_850/default.py
cedar_graph/plots/cn/k_wind/__init__.py
cedar_graph/plots/cn/k_wind/default.py
cedar_graph/plots/cn/prep_24h/__init__.py
cedar_graph/plots/cn/prep_24h/default.py
cedar_graph/plots/cn/pte_wind/__init__.py
cedar_graph/plots/cn/pte_wind/default.py
cedar_graph/plots/cn/qv_div/__init__.py
cedar_graph/plots/cn/qv_div/default.py
cedar_graph/plots/cn/radar_reflectivity/__init__.py
cedar_graph/plots/cn/radar_reflectivity/default.py
cedar_graph/plots/cn/rain_24h/__init__.py
cedar_graph/plots/cn/rain_24h/default.py
cedar_graph/plots/cn/rain_wind_10m/__init__.py
cedar_graph/plots/cn/rain_wind_10m/default.py
cedar_graph/plots/cn/shr/__init__.py
cedar_graph/plots/cn/shr/default.py
cedar_graph/plots/cn/t_2m/__init__.py
cedar_graph/plots/cn/t_2m/default.py
cedar_graph/plots/cn/t_dew_t/__init__.py
cedar_graph/plots/cn/t_dew_t/default.py
cedar_graph/plots/cn/wind_10m/__init__.py
cedar_graph/plots/cn/wind_10m/default.py
cedar_graph-2024.10.0.dist-info/LICENSE
cedar_graph-2024.10.0.dist-info/METADATA
cedar_graph-2024.10.0.dist-info/WHEEL
cedar_graph-2024.10.0.dist-info/top_level.txt
cedar_graph-2024.10.0.dist-info/RECORD
