Metadata-Version: 2.1
Name: cedar-graph
Version: 2024.10.0
Summary: Plot tool for CEMC.
Author-email: Wang Dapeng <perillaroc@gmail.com>
License: Apache-2.0
Project-URL: Homepage, https://github.com/cemc-oper/cedar-graph
Project-URL: Repository, https://github.com/cemc-oper/cedar-graph.git
Keywords: graphic,cemc,cedarkit
Classifier: Development Status :: 3 - Alpha
Classifier: Intended Audience :: Developers
Classifier: License :: OSI Approved :: Apache Software License
Classifier: Programming Language :: Python :: 3.11
Classifier: Programming Language :: Python :: 3.12
License-File: LICENSE
Requires-Dist: numpy
Requires-Dist: pandas
Requires-Dist: matplotlib
Requires-Dist: cartopy
Requires-Dist: xarray
Requires-Dist: reki >=2024.4.0
Requires-Dist: cedarkit-comp >=2024.4.0
Requires-Dist: cedarkit-maps >=2024.4.0
Requires-Dist: importlib-metadata ; python_version < "3.8"
Provides-Extra: cov
Requires-Dist: pytest-cov ; extra == 'cov'
Requires-Dist: codecov ; extra == 'cov'
Provides-Extra: test
Requires-Dist: pytest ; extra == 'test'
